<?xml version="1.0" encoding="UTF-8" ?>
<!DOCTYPE suite SYSTEM "http://testng.org/testng-1.0.dtd" >
<suite name="groupClassTest">
    <test name="classGroup">
        <groups>
            <run>
                <include name="teacher"/>
            </run>
        </groups>
        <classes>
            <class name="testngStudy.classGroups.groupClassOnStu"/>
            <class name="testngStudy.classGroups.groupClass1OnStu"/>
            <class name="testngStudy.classGroups.groupClassOnTeacher"/>
        </classes>
    </test>

</suite>
